LICENSE
MANIFEST.in
README.md
pyproject.toml
setup.cfg
setup.py
rfi_file_monitor/__init__.py
rfi_file_monitor/application.py
rfi_file_monitor/applicationwindow.py
rfi_file_monitor/engine.py
rfi_file_monitor/engine_advanced_settings.py
rfi_file_monitor/file.py
rfi_file_monitor/job.py
rfi_file_monitor/operation.py
rfi_file_monitor/preferences.py
rfi_file_monitor/preferenceswindow.py
rfi_file_monitor/queue_manager.py
rfi_file_monitor/version.py
rfi_file_monitor.egg-info/PKG-INFO
rfi_file_monitor.egg-info/SOURCES.txt
rfi_file_monitor.egg-info/dependency_links.txt
rfi_file_monitor.egg-info/entry_points.txt
rfi_file_monitor.egg-info/not-zip-safe
rfi_file_monitor.egg-info/requires.txt
rfi_file_monitor.egg-info/top_level.txt
rfi_file_monitor/data/RFI-logo-transparent.png
rfi_file_monitor/data/__init__.py
rfi_file_monitor/data/filter-popover.ui
rfi_file_monitor/data/menus-appmenu.ui
rfi_file_monitor/data/menus-common.ui
rfi_file_monitor/data/rfi-instruments.yaml
rfi_file_monitor/data/models/__init__.py
rfi_file_monitor/data/models/s3/__init__.py
rfi_file_monitor/data/models/s3/2006-03-01/__init__.py
rfi_file_monitor/data/models/s3/2006-03-01/service-2.sdk-extras.json
rfi_file_monitor/docs/__init__.py
rfi_file_monitor/docs/queue_manager.pango
rfi_file_monitor/engines/__init__.py
rfi_file_monitor/engines/aws_s3_bucket_engine.py
rfi_file_monitor/engines/aws_s3_bucket_engine_advanced_settings.py
rfi_file_monitor/engines/base_s3_bucket_engine.py
rfi_file_monitor/engines/ceph_s3_bucket_engine.py
rfi_file_monitor/engines/ceph_s3_bucket_engine_advanced_settings.py
rfi_file_monitor/engines/directory_watchdog_engine.py
rfi_file_monitor/engines/directory_watchdog_engine_advanced_settings.py
rfi_file_monitor/engines/file_watchdog_engine.py
rfi_file_monitor/engines/file_watchdog_engine_advanced_settings.py
rfi_file_monitor/engines/temporary_file_engine.py
rfi_file_monitor/engines/docs/__init__.py
rfi_file_monitor/engines/docs/aws_s3_bucket_engine.pango
rfi_file_monitor/engines/docs/ceph_s3_bucket_engine.pango
rfi_file_monitor/engines/docs/directory_watchdog_engine.pango
rfi_file_monitor/engines/docs/file_watchdog_engine.pango
rfi_file_monitor/engines/docs/template.pango
rfi_file_monitor/engines/docs/temporary_file_engine.pango
rfi_file_monitor/files/__init__.py
