Metadata-Version: 2.1
Name: rfi-file-monitor
Version: 0.2.11
Summary: Easy to use file monitor GUI with user-definable operations
Home-page: https://github.com/RosalindFranklinInstitute/rfi-file-monitor
Author: Tom Schoonjans
Author-email: Tom.Schoonjans@rfi.ac.uk
License: BSD 3-Clause License
Project-URL: GitHub, https://github.com/RosalindFranklinInstitute/rfi-file-monitor
Project-URL: Bug-Tracker, https://github.com/RosalindFranklinInstitute/rfi-file-monitor/issues
Project-URL: Documentation, https://rosalindfranklininstitute.github.io/rfi-file-monitor/
Classifier: Development Status :: 3 - Alpha
Classifier: License :: OSI Approved :: BSD License
Classifier: Natural Language :: English
Classifier: Operating System :: POSIX :: Linux
Classifier: Operating System :: Microsoft
Classifier: Operating System :: MacOS :: MacOS X
Classifier: Programming Language :: Python :: 3.8
Requires-Python: >=3.8
License-File: LICENSE
